pyTimeSeriesForecast/__init__.py
pyTimeSeriesForecast/data.py
pyTimeSeriesForecast/dataPreProcessing.py
pyTimeSeriesForecast/dataVisualizing.py
pyTimeSeriesForecast/main.py
pyTimeSeriesForecast/metrics.py
pyTimeSeriesForecast/model.py
timeSeriesForecastpkgpy-0.0.2.dist-info/METADATA
timeSeriesForecastpkgpy-0.0.2.dist-info/WHEEL
timeSeriesForecastpkgpy-0.0.2.dist-info/top_level.txt
timeSeriesForecastpkgpy-0.0.2.dist-info/RECORD
