Metadata-Version: 2.1
Name: timeSeriesForecastpkgpy
Version: 0.0.2
Summary: A package that supports forecasting tasks in python
Home-page: UNKNOWN
Author: Miguel Vuori
Author-email: <mfvuori@gmail.com>
License: UNKNOWN
Keywords: python
Platform: UNKNOWN
Classifier: Development Status :: 1 - Planning
Classifier: Intended Audience :: Developers
Classifier: Programming Language :: Python :: 3
Classifier: Operating System :: Unix
Classifier: Operating System :: MacOS :: MacOS X
Classifier: Operating System :: Microsoft :: Windows
Requires-Dist: pandas
Requires-Dist: plotly
Requires-Dist: statsmodels
Requires-Dist: matplotlib
Requires-Dist: numpy
Requires-Dist: scikit-learn
Requires-Dist: tensorflow
